FSM_design.v
//                    FSM Modelling example for Checking if a door is locked or unlocked using a 3bit pin 011

module FSM(
input w0,w1,clk,reset,
output  L
);
//wire[1:0] t;

reg [1:0] state,next_state;

parameter S0=2'b00,S1=2'b01,S2=2'b10,S3=2'b11;


always@(posedge clk,negedge reset)begin
if(reset==0)  state<=S0;
else state<=next_state;
end


always @(*) begin//next state logic
    case(state)
        S0: if(w0) next_state = S1; else if(w1) next_state = S0; else next_state = S0;
        S1: if(w0) next_state = S1; else if(w1) next_state = S2; else next_state = S1;
        S2: if(w0) next_state = S1; else if(w1) next_state = S3; else next_state = S2;
        S3: if(w0) next_state = S1; else if(w1) next_state = S0; else next_state = S3;
        default: next_state = S0;
    endcase
end

//here state is just a 2 bit value
assign L=&state;          //IF L=0, it means the door is locked,if L=1 door is unlocked


endmodule

FSM_designtb.v
module tb();
reg w0,w1,clk,reset;
wire L;
FSM DUT(w0,w1,clk,reset,L);

initial begin   //getting output plus setting up gtkwave
$dumpfile("wave.vcd");
$dumpvars(0,tb);
end

initial begin//setting up the clock
clk=1'b0;
forever #5 clk=~clk;
end


initial begin//actual testing

$monitor($time,"  w0=%b,w1=%b.state=%b,L=%b   ",w0,w1,DUT.state,L);

reset=0;//FOr setting initial state to S0
w0=0;w1=0;//making sure that all buttons are not pressed
#10;
reset=1;

//trying to get L=1/state=S3
w0=1;#10;w0 =0;#10; //trying to simulate a button press
w1=1;#10;w1=0;#10;
w1=1;#10;w1=0;#10;//i am adding #10 delays so that the change can be caught on the clock cycle
//now trying random cases
w0=1;#10;w0 =0;#10;
w1=1;#10;w1=0;#10;
w1=0;#10;w1=0;#10;

w1=1;#10;w0 =0;#10; 
w1=1;#10;w1=0;#10;
w1=1;#10;w1=0;#10;


#20 $finish;
end

endmodule

wave.vcd
$date
	Thu Oct 16 14:49:46 2025
$end
$version
	Icarus Verilog
$end
$timescale
	1s
$end
$scope module tb $end
$var wire 1 ! L $end
$var reg 1 " clk $end
$var reg 1 # reset $end
$var reg 1 $ w0 $end
$var reg 1 % w1 $end
$scope module DUT $end
$var wire 1 " clk $end
$var wire 1 # reset $end
$var wire 1 $ w0 $end
$var wire 1 % w1 $end
$var wire 1 ! L $end
$var parameter 2 & S0 $end
$var parameter 2 ' S1 $end
$var parameter 2 ( S2 $end
$var parameter 2 ) S3 $end
$var reg 2 * next_state [1:0] $end
$var reg 2 + state [1:0] $end
$upscope $end
$upscope $end
$enddefinitions $end
$comment Show the parameter values. $end
$dumpall
b11 )
b10 (
b1 '
b0 &
$end
#0
$dumpvars
b0 +
b0 *
0%
0$
0#
0"
0!
$end
#5
1"
#10
b1 *
0"
1$
1#
#15
b1 +
1"
#20
0"
0$
#25
1"
#30
b10 *
0"
1%
#35
b11 *
b10 +
1"
#40
b10 *
0"
0%
#45
1"
#50
b11 *
0"
1%
#55
b0 *
1!
b11 +
1"
#60
b11 *
0"
0%
#65
1"
#70
b1 *
0"
1$
#75
0!
b1 +
1"
#80
0"
0$
#85
1"
#90
b10 *
0"
1%
#95
b11 *
b10 +
1"
#100
b10 *
0"
0%
#105
1"
#110
0"
#115
1"
#120
0"
#125
1"
#130
b11 *
0"
1%
#135
b0 *
1!
b11 +
1"
#140
0"
#145
0!
b0 +
1"
#150
0"
#155
1"
#160
0"
0%
#165
1"
#170
0"
1%
#175
1"
#180
0"
0%
